draw_from_lldp/__init__.py
draw_from_lldp/draw_from_file.py
draw_from_lldp/input/lldp.txt
draw_from_lldp/log/connection.log
draw_from_lldp/output/asw-01.drawio
draw_from_lldp/ttp/lldp.ttp
draw_from_lldp-0.1.0.dist-info/METADATA
draw_from_lldp-0.1.0.dist-info/WHEEL
draw_from_lldp-0.1.0.dist-info/RECORD
