Metadata-Version: 2.3
Name: draw-from-lldp
Version: 0.1.0
Summary: Simple script for draw topology from lldp
Author: Ruslan Bukharaev
Requires-Python: >=3.11,<4.0
Classifier: Programming Language :: Python :: 3
Classifier: Programming Language :: Python :: 3.11
Classifier: Programming Language :: Python :: 3.12
Classifier: Programming Language :: Python :: 3.13
Requires-Dist: n2g (>=0.3.3,<0.4.0)
Requires-Dist: python-igraph (>=0.11.9,<0.12.0)
Requires-Dist: ttp (>=0.9.5,<0.10.0)
